MANIFEST.in
README.rst
p4clean.py
setup.py
p4clean.egg-info/PKG-INFO
p4clean.egg-info/SOURCES.txt
p4clean.egg-info/dependency_links.txt
p4clean.egg-info/entry_points.txt
p4clean.egg-info/not-zip-safe
p4clean.egg-info/top_level.txt
test/__init__.py
test/test_p4clean.py
test/data/.p4clean