Metadata-Version: 1.0
Name: p4clean
Version: 0.0.6
Summary: A tool to reset perforce local workspace to its initial state. 
Home-page: https://github.com/okcompute/p4clean
Author: Pascal Lalancette
Author-email: okcompute@gmail.com
License: Expat License
Keywords: perforce,clean,initial
Platform: UNKNOWN
Classifier: Development Status :: 5 - Production/Stable
Classifier: Environment :: Console
Classifier: Intended Audience :: Developers
Classifier: License :: OSI Approved :: MIT License
Classifier: Operating System :: OS Independent
Classifier: Programming Language :: Python
Classifier: Programming Language :: Python :: 2.6
Classifier: Programming Language :: Python :: 2.7
Classifier: Programming Language :: Python :: 3
Classifier: Programming Language :: Python :: 3.2
Classifier: Programming Language :: Python :: 3.3
Classifier: Topic :: Software Development :: Libraries :: Python Modules
